setup.py
testing_package_distributions/Binomialdistribution.py
testing_package_distributions/Gaussiandistribution.py
testing_package_distributions/Generaldistribution.py
testing_package_distributions/__init__.py
testing_package_distributions.egg-info/PKG-INFO
testing_package_distributions.egg-info/SOURCES.txt
testing_package_distributions.egg-info/dependency_links.txt
testing_package_distributions.egg-info/not-zip-safe
testing_package_distributions.egg-info/top_level.txt